fc_xz_xz01.py
fc_xz01-1.0.dist-info/METADATA
fc_xz01-1.0.dist-info/WHEEL
fc_xz01-1.0.dist-info/top_level.txt
fc_xz01-1.0.dist-info/RECORD
